[
  {
    "id": 1,
    "q": "नेपालको संविधानको कुन धारामा प्रदेश मन्त्रिपरिषद्को गठनसम्बन्धी व्यवस्था गरिएको छ ?",
    "o": ["धारा १६२", "धारा १६३", "धारा १७०", "धारा १६८"],
    "a": 3
  },
  {
    "id": 2,
    "q": "गण्डकी प्रदेशको मुख्यमन्त्री तथा मन्त्रिपरिषद्को कार्यालय कुन जिल्लामा अवस्थित छ ?",
    "o": ["कास्की", "बागलुङ", "तनहुँ", "स्याङ्जा"],
    "a": 0
  },
  {
    "id": 3,
    "q": "गण्डकी प्रदेशको प्रथम मुख्यमन्त्री को हुन् ?",
    "o": ["कृष्णचन्द्र नेपाली पोखरेल", "पृथ्वी सुब्बा गुरुङ", "सुरेन्द्रराज पाण्डे", "खगराज अधिकारी"],
    "a": 1
  },
  {
    "id": 4,
    "q": "नेपालको संविधानअनुसार गण्डकी प्रदेशमा मुख्यमन्त्रीसहित बढीमा कति सदस्यीय मन्त्रिपरिषद् गठन गर्न सकिने संवैधानिक व्यवस्था छ ?",
    "o": ["१० जना", "१४ जना", "१२ जना", "१५ जना"],
    "a": 2
  },
  {
    "id": 5,
    "q": "प्रदेश मन्त्रिपरिषद् (गण्डकी प्रदेश सरकार) ले गरेका निर्णयहरूको प्रमाणीकरण गर्ने जिम्मेवारी कसको हुन्छ ?",
    "o": ["प्रदेश प्रमुख", "मुख्यमन्त्री", "आन्तरिक मामिला मन्त्री", "प्रदेश सरकारको प्रमुख सचिव"],
    "a": 3
  },
  {
    "id": 6,
    "q": "प्रदेश सरकारको (मुख्यमन्त्री तथा मन्त्रिपरिषद्को कार्यालय सहितको) कार्यविभाजन र कार्यसम्पादन नियमावली कसले स्वीकृत गरे बमोजिम हुन्छ ?",
    "o": ["प्रदेश मन्त्रिपरिषद्", "प्रदेश प्रमुख", "मुख्यमन्त्री", "प्रदेश सभा"],
    "a": 0
  },
  {
    "id": 7,
    "q": "गण्डकी प्रदेश मुख्यमन्त्री तथा मन्त्रिपरिषद्को कार्यालयको प्रमुख प्रशासकीय अधिकारी को हुने व्यवस्था छ ?",
    "o": ["मुख्यमन्त्री आफैँ", "नेपाल सरकारको मुख्य सचिव", "प्रदेश सरकारको प्रमुख सचिव", "मन्त्रिपरिषद्को वरिष्ठ मन्त्री"],
    "a": 2
  },
  {
    "id": 8,
    "q": "संविधानको धारा १६२ अनुसार गण्डकी प्रदेशको कार्यकारिणी अधिकार कसमा निहित रहने व्यवस्था छ ?",
    "o": ["प्रदेश प्रमुख", "मुख्यमन्त्री", "प्रदेश सभा", "प्रदेश मन्त्रिपरिषद्"],
    "a": 3
  },
  {
    "id": 9,
    "q": "गण्डकी प्रदेशको मुख्यमन्त्रीको नियुक्ति कसले गर्ने संवैधानिक व्यवस्था छ ?",
    "o": ["राष्ट्रपति", "प्रधानमन्त्री", "प्रदेश प्रमुख", "प्रदेश सभाको सभामुख"],
    "a": 2
  },
  {
    "id": 10,
    "q": "मुख्यमन्त्री र मन्त्रीहरूले आफ्नो कार्यभार सम्हाल्नु अघि कोसमक्ष पद तथा गोपनीयताको शपथ लिनुपर्ने व्यवस्था छ ?",
    "o": ["प्रदेश प्रमुख", "राष्ट्रपति", "मुख्य न्यायाधीश", "प्रदेश सभामुख"],
    "a": 0
  },
  {
    "id": 11,
    "q": "गण्डकी प्रदेश मन्त्रिपरिषद् सामूहिक रूपमा कोप्रति उत्तरदायी हुने संवैधानिक व्यवस्था छ ?",
    "o": ["नेपाल सरकार", "प्रदेश सभा", "प्रदेश प्रमुख", "मुख्यमन्त्री"],
    "a": 1
  },
  {
    "id": 12,
    "q": "प्रदेश र स्थानीय तहबीचको समन्वय गर्ने प्रमुख जिम्मेवारी प्रदेश सरकारको कुन निकायको हो ?",
    "o": ["आन्तरिक मामिला मन्त्रालय", "भौतिक पूर्वाधार विकास मन्त्रालय", "मुख्यमन्त्री तथा मन्त्रिपरिषद्को कार्यालय", "प्रदेश नीति तथा योजना आयोग"],
    "a": 2
  },
  {
    "id": 13,
    "q": "मुख्यमन्त्रीको पद रिक्त भएमा अर्को प्रदेश मन्त्रिपरिषद् गठन नभएसम्म कसले दैनिक प्रशासनिक कार्य सञ्चालन गर्ने व्यवस्था छ ?",
    "o": ["प्रदेश प्रमुखले तोकेको मन्त्री", "प्रदेश सरकारको प्रमुख सचिव", "प्रदेश सभामुख", "सोही मन्त्रिपरिषद्"],
    "a": 3
  },
  {
    "id": 14,
    "q": "प्रदेश सभाको सदस्य नभएको व्यक्ति मन्त्री पदमा नियुक्त हुन सक्ने व्यवस्था छ कि छैन ?",
    "o": ["नियुक्त हुन सक्छ, तर ६ महिनाभित्र प्रदेश सभा सदस्य हुनुपर्छ", "नियुक्त हुन सक्दैन", "नियुक्त हुन सक्छ, तर मुख्यमन्त्रीको सिफारिसमा मात्र", "प्रदेश प्रमुखले चाहेमा नियुक्त हुन सक्छ"],
    "a": 0
  },
  {
    "id": 15,
    "q": "गण्डकी प्रदेशका मुख्यमन्त्री तथा मन्त्रीहरूको पारिश्रमिक र सुविधा कसरी निर्धारण हुन्छ ?",
    "o": ["नेपाल सरकारको निर्णय बमोजिम", "प्रदेश प्रमुखको निर्णय बमोजिम", "प्रदेश ऐन बमोजिम", "मुख्यमन्त्रीको तजबिजमा"],
    "a": 2
  },
  {
    "id": 16,
    "q": "'प्रदेश सुशासन केन्द्र' प्रदेश सरकारको कुन निकायअन्तर्गत रहन्छ ?",
    "o": ["आन्तरिक मामिला मन्त्रालय", "प्रदेश प्रमुखको कार्यालय", "सामाजिक विकास मन्त्रालय", "मुख्यमन्त्री तथा मन्त्रिपरिषद्को कार्यालय"],
    "a": 3
  },
  {
    "id": 17,
    "q": "गण्डकी प्रदेशमा प्रदेश सरकारको सम्पूर्ण प्रशासनिक नेतृत्व कुन निकायले गर्दछ ?",
    "o": ["आन्तरिक मामिला तथा कानुन मन्त्रालय", "मुख्यमन्त्री तथा मन्त्रिपरिषद्को कार्यालय", "प्रदेश प्रमुखको कार्यालय", "प्रदेश लोकसेवा आयोग"],
    "a": 1
  },
  {
    "id": 18,
    "q": "प्रदेशको प्रमुख प्रशासकीय अधिकारीको रूपमा रहने 'प्रमुख सचिव' कसले खटाउने वा नियुक्त गर्ने कानुनी व्यवस्था छ ?",
    "o": ["प्रदेश प्रमुख", "मुख्यमन्त्री", "नेपाल सरकार", "प्रदेश लोकसेवा आयोग"],
    "a": 2
  },
  {
    "id": 19,
    "q": "प्रदेश सरकारको प्रमुख सचिवको पद कुन श्रेणीको हुने व्यवस्था छ ?",
    "o": ["नेपाल सरकारको राजपत्राङ्कित प्रथम श्रेणी", "प्रदेश सरकारको विशिष्ट श्रेणी", "नेपाल सरकारको राजपत्राङ्कित विशिष्ट श्रेणी", "प्रदेश सरकारको एघारौँ तह"],
    "a": 2
  },
  {
    "id": 20,
    "q": "प्रदेश मन्त्रिपरिषद्को सचिवको रूपमा कसले काम गर्ने कानुनी व्यवस्था छ ?",
    "o": ["आन्तरिक मामिला मन्त्रालयको सचिव", "प्रदेश सरकारको प्रमुख सचिव", "मुख्यमन्त्रीको स्वकीय सचिव", "मुख्यमन्त्री तथा मन्त्रिपरिषद् कार्यालयको सचिव"],
    "a": 1
  },
  {
    "id": 21,
    "q": "गण्डकी प्रदेशका अन्य मन्त्रालयहरूमा रहने सचिवहरू कसले खटाउने व्यवस्था छ ?",
    "o": ["नेपाल सरकार", "गण्डकी प्रदेश सरकार", "प्रदेश लोकसेवा आयोग", "मुख्यमन्त्री तथा मन्त्रिपरिषद्को कार्यालय"],
    "a": 0
  },
  {
    "id": 22,
    "q": "प्रदेश सरकारका विभिन्न मन्त्रालयहरूले मन्त्रिपरिषद्मा पेश गर्ने प्रस्ताव कसको मार्फत पेश गर्नुपर्ने नियम छ ?",
    "o": ["सम्बन्धित मन्त्री", "मुख्यमन्त्री", "आन्तरिक मामिला मन्त्री", "प्रदेश सरकारको प्रमुख सचिव"],
    "a": 3
  },
  {
    "id": 23,
    "q": "प्रदेश सरकारको प्रशासकीय संरचना अनुसार मन्त्रालयको सर्वोच्च कर्मचारी को हुन्छ ?",
    "o": ["महानिर्देशक", "प्रमुख जिल्ला अधिकारी", "प्रदेश सचिव", "प्रशासकीय अधिकृत"],
    "a": 2
  },
  {
    "id": 24,
    "q": "प्रदेश निजामती सेवाको गठन, सञ्चालन र सेवाका शर्तहरू कुन कानुन बमोजिम हुने व्यवस्था नेपालको संविधानमा छ ?",
    "o": ["संघीय कानुन", "प्रदेश कानुन", "स्थानीय कानुन", "मन्त्रिपरिषद्को निर्णय"],
    "a": 1
  },
  {
    "id": 25,
    "q": "प्रदेश स्तरमा सुशासन कायम गर्ने र मन्त्रालयहरूबीच समन्वय गर्ने प्रमुख प्रशासकीय जिम्मेवारी कसको हुन्छ ?",
    "o": ["प्रदेश सरकारको प्रमुख सचिव", "प्रदेश प्रमुख", "आन्तरिक मामिला सचिव", "मुख्य न्यायाधिवक्ता"],
    "a": 0
  },
  {
    "id": 26,
    "q": "प्रदेश मन्त्रिपरिषद्ले गरेका निर्णयहरूको अभिलेख राख्ने र प्रमाणित प्रतिलिपि सुरक्षित गर्ने जिम्मेवारी कसको हो ?",
    "o": ["प्रदेश प्रमुखको कार्यालय", "मुख्यमन्त्रीको स्वकीय सचिवालय", "प्रदेश सरकारको प्रमुख सचिव", "आन्तरिक मामिला मन्त्रालय"],
    "a": 2
  },
  {
    "id": 27,
    "q": "नेपाल सरकारले खटाएको प्रमुख सचिवलाई प्रदेशमा हाजिर गराउने र प्रशासकीय जिम्मेवारी तोक्ने कार्य कसले गर्दछ ?",
    "o": ["प्रदेश प्रमुख", "प्रदेश सभामुख", "सामान्य प्रशासन मन्त्रालय", "मुख्यमन्त्री"],
    "a": 3
  },
  
  {
    "id": 28,
    "q": "गण्डकी प्रदेशको नाम ‘गण्डकी’ भनी कहिले घोषणा गरिएको थियो?",
    "o": ["२०७५ असार १८", "२०७२ असोज ३", "२०७५ असार २२", "२०७४ फागुन ४"],
    "a": 2
  },
  {
    "id": 29,
    "q": "गण्डकी प्रदेशको कुल क्षेत्रफल कति रहेको छ?",
    "o": ["२१,५०४ वर्ग कि.मी.", "२०,३०० वर्ग कि.मी.", "२२,५०४ वर्ग कि.मी.", "१९,५०४ वर्ग कि.मी."],
    "a": 0
  },
  {
    "id": 30,
    "q": "राष्ट्रिय जनगणना २०७८ अनुसार गण्डकी प्रदेशको साक्षरता दर कति रहेको छ?",
    "o": ["७६.२%", "६१.८%", "७८.५%", "८३.४%"],
    "a": 3
  },
  {
    "id": 31,
    "q": "गण्डकी प्रदेशमा स्थानीय तहहरूको संख्या कति रहेको छ?",
    "o": ["१ महानगर, २७ नगरपालिका, ५७ गाउँपालिका (जम्मा ८५)", "१ महानगर, २६ नगरपालिका, ५८ गाउँपालिका (जम्मा ८५)", "१ महानगर, २५ नगरपालिका, ५९ गाउँपालिका (जम्मा ८५)", "महानगर छैन, २६ नगरपालिका, ५९ गाउँपालिका (जम्मा ८५)"],
    "a": 1
  },
  {
    "id": 32,
    "q": "गण्डकी प्रदेश सभामा कुल कति सदस्य रहने व्यवस्था छ?",
    "o": ["११० (६६ प्रत्यक्ष, ४४ समानुपातिक)", "५३ (३३ प्रत्यक्ष, २० समानुपातिक)", "६० (३६ प्रत्यक्ष, २४ समानुपातिक)", "४० (२४ प्रत्यक्ष, १६ समानुपातिक)"],
    "a": 2
  },
  {
    "id": 33,
    "q": "गण्डकी प्रदेशको एक मात्र तराई जिल्ला कुन हो?",
    "o": ["नवलपुर (नवलपरासी पूर्व)", "तनहुँ", "गोरखा", "कास्की"],
    "a": 0
  },
  {
    "id": 34,
    "q": "'जलविद्युतको केन्द्र' (Powerhouse) भनेर गण्डकीको कुन जिल्लालाई चिनिन्छ?",
    "o": ["कास्की", "मुस्ताङ", "म्याग्दी", "लमजुङ"],
    "a": 3
  },
  {
    "id": 35,
    "q": "गण्डकी प्रदेशका वर्तमान मुख्यमन्त्री सुरेन्द्र राज पाण्डे सर्वोच्च अदालतको परमादेशबाट कहिले पुनर्स्थापित हुनुभएको हो?",
    "o": ["२०८० बैशाख १४", "२०८१ जेठ १६", "२०८१ असार १", "२०८० पुष १०"],
    "a": 1
  },
  {
    "id": 36,
    "q": "'मुख्यमन्त्री वातावरण मैत्री नमुना कृषि गाउँ कार्यक्रम' कुन मोडेलमा सञ्चालन गरिएको छ?",
    "o": ["प्रत्येक वडामा एक गाउँ", "प्रत्येक जिल्लामा एक गाउँ", "प्रत्येक निर्वाचन क्षेत्रमा एक गाउँ", "प्रत्येक स्थानीय तहमा एक गाउँ"],
    "a": 2
  },
  {
    "id": 37,
    "q": "'मुख्यमन्त्री नवप्रवर्तन साझेदारी कार्यक्रम (CM-IPP)' को मुख्य अवधारणा के हो?",
    "o": ["च्यालेन्ज फण्ड (Challenge Fund)", "पूर्वाधार विकास कोष", "गरिबी निवारण कोष", "विपद् व्यवस्थापन कोष"],
    "a": 0
  },
  {
    "id": 38,
    "q": "नेपालको संविधानको कुन धारा अनुसार प्रदेशको कार्यकारिणी अधिकार मन्त्रिपरिषद्मा निहित हुन्छ?",
    "o": ["धारा १६१", "धारा १६३", "धारा १६८", "धारा १६२"],
    "a": 3
  },
  {
    "id": 39,
    "q": "चीनसँगको व्यापारिक नाका 'कोरला' गण्डकी प्रदेशको कुन जिल्लामा पर्दछ?",
    "o": ["मनाङ", "मुस्ताङ", "गोरखा", "म्याग्दी"],
    "a": 1
  },
  {
    "id": 40,
    "q": "मानव विकास सूचकांक (HDI) मा गण्डकी प्रदेशको अवस्था कस्तो छ?",
    "o": ["०.५९० (नेपालमा तेस्रो)", "०.६१८ (नेपालमा पहिलो)", "०.६१८ (नेपालमा दोस्रो)", "०.६०२ (नेपालमा दोस्रो)"],
    "a": 2
  },
  {
    "id": 41,
    "q": "गण्डकी प्रदेशको पहिलो प्रदेश प्रमुख को हुनुहुन्थ्यो?",
    "o": ["बाबुराम कुँवर", "अमिक शेरचन", "पृथ्वीमान गुरुङ", "डिल्ली राज भट्ट"],
    "a": 0
  },
  {
    "id": 42,
    "q": "गण्डकी प्रदेशको राजधानी 'पोखरा' कहिले घोषणा गरिएको थियो?",
    "o": ["२०७५ असार २२", "२०७४ माघ ४", "२०७५ जेठ १६", "२०७५ असार १८"],
    "a": 3
  },
  {
    "id": 43,
    "q": "नेपालको संविधानको कुन धारामा प्रदेशको कार्यकारिणी अधिकार सम्बन्धी व्यवस्था गरिएको छ?",
    "o": ["धारा १६०", "धारा १६२", "धारा १६१", "धारा १६३"],
    "a": 1
  },
  {
    "id": 44,
    "q": "नेपालको संविधानमा प्रदेश मन्त्रिपरिषदको गठन सम्बन्धी व्यवस्था कुन धारामा छ?",
    "o": ["धारा १६६", "धारा १६९", "धारा १६८", "धारा १६७"],
    "a": 2
  },
  {
    "id": 45,
    "q": "प्रदेश सरकारको कार्यविभाजन र कार्य सम्पादन सम्बन्धी व्यवस्था संविधानको कुन धारामा उल्लेख छ?",
    "o": ["धारा १७४", "धारा १७३", "धारा १७२", "धारा १७५"],
    "a": 0
  },
  {
    "id": 46,
    "q": "प्रदेश मन्त्रिपरिषदका कार्यलाई सुव्यवस्थित गर्न कतिवटा समिति बनेका छन्?",
    "o": ["२ वटा", "४ वटा", "५ वटा", "३ वटा"],
    "a": 3
  },
  {
    "id": 47,
    "q": "गण्डकी प्रदेश सरकार (कार्यविभाजन) नियमावली, २०७४ को कति नियम अन्तर्गत रही संशोधन गरिएको हो?",
    "o": ["नियम ७", "नियम ८", "नियम ९", "नियम ६"],
    "a": 1
  },
  {
    "id": 48,
    "q": "गण्डकी प्रदेश सरकारको कार्यविभाजन नियमावली संशोधन हुँदा कुन-कुन अनुसूची संशोधन भएका हुन्?",
    "o": ["अनुसूची १ मात्र", "अनुसूची २ मात्र", "अनुसूची १ र २", "अनुसूची १ र ३"],
    "a": 2
  },
  {
    "id": 49,
    "q": "संशोधित नियमावलीको अनुसूची १ अन्तर्गत कतिवटा मन्त्रालयहरु रहेका छन्?",
    "o": ["११", "९", "७", "१२"],
    "a": 0
  },
  {
    "id": 50,
    "q": "अनुसूची २ बमोजिम मुख्यमन्त्री तथा मन्त्रिपरिषदको कार्यालयको कार्यजिम्मेवारी कतिवटा तोकिएको छ?",
    "o": ["४२", "४५", "३५", "४०"],
    "a": 1
  },
  {
    "id": 51,
    "q": "गण्डकी प्रदेश सरकार कार्यविभाजन नियमावलीको संशोधित प्रकाशन मिति कहिले हो?",
    "o": ["२०७८/०४/०५", "२०७८/०५/१५", "२०७८/०६/०५", "२०७८/०2/०५"],
    "a": 3
  },
  
  {
    "id": 52,
    "q": "मुख्यमन्त्रीले नियुक्त भएको कति दिनभित्र प्रदेश सभाबाट विश्वासको मत लिनुपर्ने संवैधानिक व्यवस्था छ ?",
    "o": ["१५ दिन", "४५ दिन", "३० दिन", "२१ दिन"],
    "a": 2
  },
  {
    "id": 53,
    "q": "गण्डकी प्रदेश नीति तथा योजना आयोगको अध्यक्ष को रहने व्यवस्था छ ?",
    "o": ["मुख्यमन्त्री", "अर्थ मन्त्री", "प्रमुख सचिव", "प्रदेश प्रमुख"],
    "a": 0
  },
  {
    "id": 54,
    "q": "गण्डकी प्रदेशको मुख्य न्यायाधिवक्ताको नियुक्ति कसको सिफारिसमा प्रदेश प्रमुखबाट हुने व्यवस्था छ ?",
    "o": ["प्रमुख सचिव", "मुख्यमन्त्री", "मुख्य न्यायाधीश", "प्रदेश सभामुख"],
    "a": 1
  },
  {
    "id": 55,
    "q": "नेपालको संविधानअनुसार कुन अवस्थामा मुख्यमन्त्रीको सिफारिसमा प्रदेश प्रमुखले प्रदेश सभालाई विघटन गर्न सक्ने व्यवस्था छ ?",
    "o": ["प्रदेश प्रमुखलाई लागेमा", "सभामुखले सिफारिस गरेमा", "प्रदेश सभाको कार्यकाल सकिनु ६ महिना अगाडि", "विश्वासको मत प्राप्त गर्न नसकेमा (धारा १६८ को उपधारा ७)"],
    "a": 3
  },
  {
    "id": 56,
    "q": "गण्डकी प्रदेशमा नागरिकका गुनासा सुन्न र समाधान गर्न मुख्यमन्त्री तथा मन्त्रिपरिषद्को कार्यालयमा सञ्चालन गरिएको कार्यक्रम कुन हो ?",
    "o": ["जनताको मुख्यमन्त्री", "हेलो मुख्यमन्त्री", "सुशासन डेस्क", "मुख्यमन्त्रीसँग नागरिक"],
    "a": 1
  },
  {
    "id": 57,
    "q": "विपद् व्यवस्थापन र राहत वितरणको लागि प्रदेशस्तरमा स्थापना गरिने 'मुख्यमन्त्री राहत कोष'को सञ्चालन कसको प्रत्यक्ष नियन्त्रणमा हुन्छ ?",
    "o": ["आर्थिक मामिला मन्त्रालय", "आन्तरिक मामिला मन्त्रालय", "मुख्यमन्त्री तथा मन्त्रिपरिषद्को कार्यालय", "प्रदेश प्रमुखको कार्यालय"],
    "a": 2
  },
  {
    "id": 58,
    "q": "प्रदेश प्रमुखले प्रदेशका विभिन्न संवैधानिक आयोगहरूको वार्षिक प्रतिवेदन प्रदेश सभामा कसको मार्फत पेश गर्न लगाउने संवैधानिक व्यवस्था छ ?",
    "o": ["मुख्यमन्त्री", "सभामुख", "प्रमुख सचिव", "सम्बन्धित मन्त्री"],
    "a": 0
  },
  {
    "id": 59,
    "q": "प्रदेश सभाको अधिवेशन आह्वान र अन्त्य कसको सिफारिसमा प्रदेश प्रमुखले गर्ने व्यवस्था छ ?",
    "o": ["आन्तरिक मामिला मन्त्री", "प्रदेश सभामुख", "प्रमुख सचिव", "मुख्यमन्त्री (प्रदेश मन्त्रिपरिषद्)"],
    "a": 3
  },
  {
    "id": 60,
    "q": "प्रदेश मन्त्रिपरिषद्को बैठक सामान्यतया कसले आह्वान गर्ने (बोलाउने) र अध्यक्षता गर्ने गर्दछ ?",
    "o": ["वरिष्ठ मन्त्री", "प्रदेश प्रमुख", "मुख्यमन्त्री", "प्रमुख सचिव"],
    "a": 2
  },
  {
    "id": 61,
    "q": "गण्डकी प्रदेशमा मन्त्रालयहरूको संख्या हेरफेर गर्ने वा मन्त्रालय गाभ्ने/फुटाउने अधिकार कसलाई हुन्छ ?",
    "o": ["नेपाल सरकार", "प्रदेश मन्त्रिपरिषद् (मुख्यमन्त्री)", "प्रदेश प्रमुख", "प्रदेश सभा"],
    "a": 1
  },
  
  {
    "id": 62,
    "q": "प्रदेश र स्थानीय तहबीचको विवाद समाधान र समन्वय गर्न गठन हुने 'प्रदेश समन्वय परिषद्' को अध्यक्ष को रहने कानुनी व्यवस्था छ?",
    "o": ["आन्तरिक मामिला मन्त्री", "मुख्यमन्त्री", "प्रदेश प्रमुख", "प्रमुख सचिव"],
    "a": 1
  },
  {
    "id": 63,
    "q": "नेपालको संविधानको धारा १६९ अनुसार गण्डकी प्रदेशका मुख्यमन्त्रीले आफ्नो पदबाट राजीनामा दिनु परेमा कोसमक्ष लिखित राजीनामा पेश गर्नुपर्दछ?",
    "o": ["प्रदेश प्रमुख", "प्रदेश सभाको सभामुख", "प्रधानमन्त्री", "मन्त्रिपरिषद्"],
    "a": 0
  },
  {
    "id": 64,
    "q": "गण्डकी प्रदेशमा मन्त्रालयहरूको नीति, कार्यक्रम र बजेट कार्यान्वयनको प्रत्यक्ष अनुगमन र मूल्याङ्कन गर्ने प्रमुख जिम्मेवारी कुन निकायलाई तोकिएको छ?",
    "o": ["अर्थ मन्त्रालय", "प्रदेश नीति तथा योजना आयोग", "आन्तरिक मामिला मन्त्रालय", "मुख्यमन्त्री तथा मन्त्रिपरिषद्को कार्यालय"],
    "a": 3
  },
  {
    "id": 65,
    "q": "गण्डकी प्रदेश विकास परिषद्को बैठकको अध्यक्षता कसले गर्ने व्यवस्था छ?",
    "o": ["अर्थमन्त्री", "प्रमुख सचिव", "मुख्यमन्त्री", "प्रदेश नीति तथा योजना आयोगका उपाध्यक्ष"],
    "a": 2
  },
  {
    "id": 66,
    "q": "संघ, प्रदेश र स्थानीय तहबीचको अन्तरसम्बन्ध व्यवस्थित गर्ने ऐन अनुसार गठित 'राष्ट्रिय समन्वय परिषद्' मा गण्डकी प्रदेशको तर्फबाट कसले प्रतिनिधित्व गर्ने व्यवस्था छ?",
    "o": ["मुख्यमन्त्री", "प्रदेश प्रमुख", "मुख्य सचिव", "आन्तरिक मामिला मन्त्री"],
    "a": 0
  },
  {
    "id": 67,
    "q": "गण्डकी प्रदेश नीति तथा योजना आयोगका उपाध्यक्ष र सदस्यहरूको नियुक्ति गर्ने अधिकार कसमा निहीत छ?",
    "o": ["मुख्यमन्त्रीको एकल निर्णय", "प्रदेश मन्त्रिपरिषद्", "प्रदेश प्रमुख", "प्रदेश सभा"],
    "a": 1
  },
  {
    "id": 68,
    "q": "प्रदेश सरकारको कार्यसम्पादन नियमावली बमोजिम दुई वा सोभन्दा बढी मन्त्रालयको कार्यक्षेत्रका विषयमा विवाद उत्पन्न भएमा त्यसको अन्तिम निर्णय कसले गर्दछ?",
    "o": ["प्रदेश प्रमुख", "आन्तरिक मामिला मन्त्री", "मुख्य न्यायाधिवक्ता", "मुख्यमन्त्री"],
    "a": 3
  },
  {
    "id": 69,
    "q": "संविधानको धारा १६८ को उपधारा (८) बमोजिम मुख्यमन्त्री वा मन्त्रीले कुन ढाँचामा शपथ लिनुपर्ने व्यवस्था छ?",
    "o": ["संघीय कानुन बमोजिम", "प्रदेश कानुन बमोजिम", "राष्ट्रपतिले तोके बमोजिम", "नेपाल सरकारले तोके बमोजिम"],
    "a": 1
  },
  {
    "id": 70,
    "q": "मुख्यमन्त्रीको अनुपस्थितिमा मुख्यमन्त्री तथा मन्त्रिपरिषद्को कार्यालयको दैनिक प्रशासनिक कार्यको नेतृत्व कसले गर्दछ?",
    "o": ["प्रदेश प्रमुख", "वरिष्ठ मन्त्री", "प्रमुख सचिव", "आन्तरिक मामिला सचिव"],
    "a": 2
  },
  {
    "id": 71,
    "q": "गण्डकी प्रदेश मन्त्रिपरिषद्को बैठकको एजेन्डा (कार्यसूची) तयार पार्ने र मुख्यमन्त्रीसमक्ष पेश गर्ने जिम्मेवारी कसको हो?",
    "o": ["प्रमुख सचिव", "सरकारको प्रवक्ता", "मुख्यमन्त्रीको स्वकीय सचिव", "आन्तरिक मामिला सचिव"],
    "a": 0
  }
]


